LICENSE.txt
MANIFEST.in
README.md
VERSION
setup.py
hitch/debugrequirements.txt
hitch/engine.py
hitch/hitchreqs.in
hitch/hitchreqs.txt
hitch/key.py
hitch/versionbullshit.py
hitch/story/download-version-80.story
hitch/story/gui.story
hitch/story/headless.story
hitch/story/larger-window-size-disable-dev-shm-usage-and-sandbox.story
hitch/story/latest-version-available-in-package.story
hitch/story/without-sandbox.story
hitchchrome/__init__.py
hitchchrome/chromebuild.py
hitchchrome/exceptions.py
hitchchrome/utils.py
hitchchrome/versions.json
hitchchrome.egg-info/PKG-INFO
hitchchrome.egg-info/SOURCES.txt
hitchchrome.egg-info/dependency_links.txt
hitchchrome.egg-info/not-zip-safe
hitchchrome.egg-info/requires.txt
hitchchrome.egg-info/top_level.txt